nonebot_plugin_epicfree/__init__.py
nonebot_plugin_epicfree/config.py
nonebot_plugin_epicfree/data_source.py
nonebot_plugin_epicfree/schedule.py
nonebot_plugin_epicfree-0.2.12.dist-info/WHEEL
nonebot_plugin_epicfree-0.2.12.dist-info/METADATA
nonebot_plugin_epicfree-0.2.12.dist-info/RECORD
