Metadata-Version: 2.3
Name: nonebot-plugin-epicfree
Version: 0.2.12
Summary: EpicGameStore free games promotions plugin for NoneBot2
Author: FlanChanXwO, monsterxcn, studylessshape
Author-email: FlanChanXwO <badapple495@outlook.com>, monsterxcn <monsterxcn@gmail.com>, studylessshape <57394096+studylessshape@users.noreply.github.com>
License: MIT
Requires-Dist: httpx>=0.27.0,<1.0.0
Requires-Dist: nonebot-adapter-onebot>=2.4.6
Requires-Dist: nonebot-plugin-apscheduler>=0.5.0,<1.0.0
Requires-Dist: nonebot2>=2.4.4
Requires-Dist: pytz
Requires-Dist: nonebot-plugin-localstore>=0.7.4
Requires-Python: >=3.10
Project-URL: Documentation, https://github.com/monsterxcn/nonebot-plugin-epicfree#readme
Project-URL: Homepage, https://github.com/monsterxcn/nonebot-plugin-epicfree
Project-URL: Repository, https://github.com/monsterxcn/nonebot-plugin-epicfree
